{
    "img_id": "1473.jpg",
    "human_num": 18,
    "points": [
        {
            "x": 103.0,
            "y": 548.0
        },
        {
            "x": 186.5,
            "y": 523.0
        },
        {
            "x": 129.5,
            "y": 417.5
        },
        {
            "x": 245.0,
            "y": 425.0
        },
        {
            "x": 174.5,
            "y": 237.0
        },
        {
            "x": 210.5,
            "y": 212.5
        },
        {
            "x": 194.0,
            "y": 181.0
        },
        {
            "x": 176.5,
            "y": 193.5
        },
        {
            "x": 147.5,
            "y": 194.5
        },
        {
            "x": 125.5,
            "y": 187.0
        },
        {
            "x": 69.5,
            "y": 261.0
        },
        {
            "x": 71.5,
            "y": 209.5
        },
        {
            "x": 101.5,
            "y": 117.0
        },
        {
            "x": 65.0,
            "y": 70.5
        },
        {
            "x": 64.0,
            "y": 47.5
        },
        {
            "x": 94.0,
            "y": 56.5
        },
        {
            "x": 86.5,
            "y": 66.0
        },
        {
            "x": 84.5,
            "y": 83.5
        }
    ]
}