{
    "img_id": "472.jpg",
    "human_num": 111,
    "points": [
        {
            "x": 153.82531194295905,
            "y": 687.7290552584672
        },
        {
            "x": 127.13012477718368,
            "y": 658.2959001782532
        },
        {
            "x": 131.92156862745105,
            "y": 556.3065953654188
        },
        {
            "x": 10.081996434937714,
            "y": 455.00178253119435
        },
        {
            "x": 105.91087344028524,
            "y": 369.44028520499114
        },
        {
            "x": 186.6809269162211,
            "y": 383.8146167557932
        },
        {
            "x": 158.61675579322642,
            "y": 333.8467023172906
        },
        {
            "x": 207.21568627450986,
            "y": 305.09803921568624
        },
        {
            "x": 277.7183600713013,
            "y": 298.9376114081997
        },
        {
            "x": 253.7611408199644,
            "y": 235.27985739750446
        },
        {
            "x": 269.50445632798585,
            "y": 278.4028520499109
        },
        {
            "x": 338.638146167558,
            "y": 376.969696969697
        },
        {
            "x": 365.3333333333333,
            "y": 326.3172905525847
        },
        {
            "x": 481.0124777183601,
            "y": 432.41354723707667
        },
        {
            "x": 366.7023172905526,
            "y": 505.65418894830657
        },
        {
            "x": 502.91622103386806,
            "y": 322.89483065953664
        },
        {
            "x": 551.5151515151515,
            "y": 322.2103386809269
        },
        {
            "x": 567.9429590017826,
            "y": 648.0285204991087
        },
        {
            "x": 405.0338680926916,
            "y": 736.3279857397504
        },
        {
            "x": 830.7878787878788,
            "y": 617.9108734402853
        },
        {
            "x": 786.9803921568628,
            "y": 300.30659536541896
        },
        {
            "x": 743.1729055258468,
            "y": 290.7237076648842
        },
        {
            "x": 782.1889483065954,
            "y": 214.7450980392157
        },
        {
            "x": 904.7130124777184,
            "y": 286.61675579322645
        },
        {
            "x": 357.80392156862746,
            "y": 243.49376114082
        },
        {
            "x": 399.55793226381473,
            "y": 220.90552584670235
        },
        {
            "x": 446.1033868092692,
            "y": 192.8413547237077
        },
        {
            "x": 461.16221033868095,
            "y": 180.5204991087344
        },
        {
            "x": 380.3921568627451,
            "y": 146.98039215686282
        },
        {
            "x": 418.7237076648842,
            "y": 162.0392156862746
        },
        {
            "x": 446.1033868092692,
            "y": 140.81996434937614
        },
        {
            "x": 461.84670231729064,
            "y": 135.34402852049914
        },
        {
            "x": 439.9429590017826,
            "y": 114.80926916221033
        },
        {
            "x": 8.02852049910878,
            "y": 175.72905525846704
        },
        {
            "x": 51.15151515151521,
            "y": 159.30124777183607
        },
        {
            "x": 17.6114081996436,
            "y": 134.65953654188954
        },
        {
            "x": 98.38146167557937,
            "y": 117.54723707664893
        },
        {
            "x": 71.686274509804,
            "y": 118.91622103386806
        },
        {
            "x": 30.360071301247764,
            "y": 40.45632798573976
        },
        {
            "x": 63.90017825311943,
            "y": 61.675579322638164
        },
        {
            "x": 73.825311942959,
            "y": 50.894830659536545
        },
        {
            "x": 89.73975044563281,
            "y": 62.87344028520501
        },
        {
            "x": 131.32263814616755,
            "y": 63.90017825311945
        },
        {
            "x": 154.76648841354722,
            "y": 50.72370766488415
        },
        {
            "x": 181.63279857397507,
            "y": 81.3547237076649
        },
        {
            "x": 181.80392156862746,
            "y": 67.49376114081997
        },
        {
            "x": 206.61675579322636,
            "y": 90.59536541889484
        },
        {
            "x": 220.6488413547237,
            "y": 85.97504456327987
        },
        {
            "x": 213.97504456327985,
            "y": 74.50980392156863
        },
        {
            "x": 121.22638146167559,
            "y": 108.90552584670233
        },
        {
            "x": 149.11942959001783,
            "y": 117.46167557932264
        },
        {
            "x": 45.076648841354725,
            "y": 100.86274509803921
        },
        {
            "x": 30.873440285205,
            "y": 89.05525846702318
        },
        {
            "x": 20.819964349376107,
            "y": 20.3065953654189
        },
        {
            "x": 10.638146167557922,
            "y": 20.392156862745107
        },
        {
            "x": 282.68092691622115,
            "y": 109.16221033868098
        },
        {
            "x": 305.6114081996436,
            "y": 105.73975044563285
        },
        {
            "x": 319.6434937611409,
            "y": 110.1889483065954
        },
        {
            "x": 329.22638146167577,
            "y": 107.45098039215692
        },
        {
            "x": 374.7450980392158,
            "y": 94.10338680926921
        },
        {
            "x": 296.37076648841366,
            "y": 93.4188948306596
        },
        {
            "x": 300.47771836007144,
            "y": 78.01782531194301
        },
        {
            "x": 267.6221033868094,
            "y": 84.86274509803926
        },
        {
            "x": 261.119429590018,
            "y": 99.57932263814622
        },
        {
            "x": 254.95900178253132,
            "y": 76.99108734402859
        },
        {
            "x": 311.7718360071303,
            "y": 60.56327985739756
        },
        {
            "x": 453.8039215686276,
            "y": 87.60071301247775
        },
        {
            "x": 524.306595365419,
            "y": 102.65953654188951
        },
        {
            "x": 580.7771836007131,
            "y": 67.75044563279863
        },
        {
            "x": 616.0285204991088,
            "y": 120.79857397504456
        },
        {
            "x": 655.0445632798576,
            "y": 106.42424242424246
        },
        {
            "x": 695.7718360071303,
            "y": 77.67557932263819
        },
        {
            "x": 710.488413547237,
            "y": 85.88948306595371
        },
        {
            "x": 275.7932263814618,
            "y": 23.47237076648842
        },
        {
            "x": 283.83600713012487,
            "y": 25.696969696969706
        },
        {
            "x": 361.9536541889484,
            "y": 36.64884135472371
        },
        {
            "x": 483.5793226381462,
            "y": 37.88948306595366
        },
        {
            "x": 589.5044563279857,
            "y": 63.72905525846705
        },
        {
            "x": 369.440285204991,
            "y": 149.97504456327985
        },
        {
            "x": 368.07130124777177,
            "y": 128.41354723707664
        },
        {
            "x": 762.1675579322638,
            "y": 96.15686274509807
        },
        {
            "x": 874.4242424242425,
            "y": 98.21033868092697
        },
        {
            "x": 927.1301247771837,
            "y": 88.6274509803922
        },
        {
            "x": 931.2370766488414,
            "y": 190.2745098039216
        },
        {
            "x": 965.1194295900178,
            "y": 257.69696969696975
        },
        {
            "x": 996.6060606060605,
            "y": 233.7397504456328
        },
        {
            "x": 745.9964349376114,
            "y": 30.70231729055259
        },
        {
            "x": 764.306595365419,
            "y": 30.01782531194298
        },
        {
            "x": 790.488413547237,
            "y": 31.72905525846704
        },
        {
            "x": 793.2263814616756,
            "y": 48.15686274509805
        },
        {
            "x": 817.01247771836,
            "y": 43.02317290552586
        },
        {
            "x": 894.0178253119429,
            "y": 50.72370766488415
        },
        {
            "x": 721.0124777183602,
            "y": 29.50445632798576
        },
        {
            "x": 880.2638146167558,
            "y": 13.311942959001785
        },
        {
            "x": 908.3707664884134,
            "y": 10.103386809269166
        },
        {
            "x": 860.4991087344029,
            "y": 7.70766488413548
        },
        {
            "x": 550.007012595248,
            "y": 6.230788819024134
        },
        {
            "x": 513.1798397680752,
            "y": 5.20781179604712
        },
        {
            "x": 574.0469726352081,
            "y": 10.834185422420763
        },
        {
            "x": 672.7642553524909,
            "y": 7.253765842001146
        },
        {
            "x": 690.1548647431002,
            "y": 5.20781179604712
        },
        {
            "x": 701.919100507336,
            "y": 5.20781179604712
        },
        {
            "x": 715.2178018060373,
            "y": 15.949070537305898
        },
        {
            "x": 740.7922273804628,
            "y": 18.50651309474843
        },
        {
            "x": 740.7922273804628,
            "y": 8.788231376466667
        },
        {
            "x": 734.1428767311122,
            "y": 3.6733462615816013
        },
        {
            "x": 776.0849346731702,
            "y": 23.10990969814499
        },
        {
            "x": 792.4525670408026,
            "y": 12.368650956886281
        },
        {
            "x": 785.8032163914519,
            "y": 3.6733462615816013
        },
        {
            "x": 836.4405790288146,
            "y": 3.6733462615816013
        },
        {
            "x": 333.8558594006166,
            "y": 1.976260738409074
        }
    ]
}