{
    "img_id": "512.jpg",
    "human_num": 196,
    "points": [
        {
            "x": 362.54647313470844,
            "y": 521.9230965113318
        },
        {
            "x": 485.97504456327994,
            "y": 575.5334861217214
        },
        {
            "x": 590.7023172905525,
            "y": 758.8062133944487
        },
        {
            "x": 994.6503692386045,
            "y": 397.2477718360071
        },
        {
            "x": 866.23478482302,
            "y": 344.88413547237076
        },
        {
            "x": 810.130888719124,
            "y": 296.26075884899416
        },
        {
            "x": 595.6893302775657,
            "y": 347.3776419658772
        },
        {
            "x": 583.2217978100332,
            "y": 287.53348612172135
        },
        {
            "x": 519.6373822256174,
            "y": 287.53348612172135
        },
        {
            "x": 482.2347848230201,
            "y": 242.6503692386044
        },
        {
            "x": 476.0010185892539,
            "y": 204.0010185892538
        },
        {
            "x": 523.3776419658773,
            "y": 206.49452508276033
        },
        {
            "x": 572.0010185892538,
            "y": 221.45556404379923
        },
        {
            "x": 605.6633562515915,
            "y": 207.74127832951353
        },
        {
            "x": 638.078940667176,
            "y": 182.80621339444863
        },
        {
            "x": 687.9490705373059,
            "y": 200.26075884899413
        },
        {
            "x": 687.9490705373059,
            "y": 164.10491469314985
        },
        {
            "x": 665.5075120957475,
            "y": 134.18283677107198
        },
        {
            "x": 615.6373822256176,
            "y": 161.61140819964345
        },
        {
            "x": 33.40361599185124,
            "y": 408.46855105678634
        },
        {
            "x": 153.09192768016297,
            "y": 347.3776419658772
        },
        {
            "x": 5.975044563279773,
            "y": 301.2477718360071
        },
        {
            "x": 92.00101858925379,
            "y": 275.0659536541889
        },
        {
            "x": 3.481538069773295,
            "y": 218.9620575502928
        },
        {
            "x": 14.70231729055248,
            "y": 179.06595365418886
        },
        {
            "x": 32.15686274509797,
            "y": 16.988031576266746
        },
        {
            "x": 7.221797810033047,
            "y": 9.507512095747241
        },
        {
            "x": 48.36465495289018,
            "y": 20.72829131652657
        },
        {
            "x": 60.83218742042264,
            "y": 15.741278329513472
        },
        {
            "x": 67.06595365418887,
            "y": 13.247771836007065
        },
        {
            "x": 59.585434173669434,
            "y": 46.91010949834477
        },
        {
            "x": 55.84517443340968,
            "y": 35.68933027756544
        },
        {
            "x": 69.55946014769535,
            "y": 64.36465495289018
        },
        {
            "x": 96.98803157626682,
            "y": 38.18283677107198
        },
        {
            "x": 92.00101858925379,
            "y": 13.247771836007065
        },
        {
            "x": 78.28673287496812,
            "y": 12.00101858925379
        },
        {
            "x": 111.94907053730576,
            "y": 9.507512095747241
        },
        {
            "x": 68.5204991087344,
            "y": 97.71530430353955
        },
        {
            "x": 109.66335625159152,
            "y": 98.33868092691615
        },
        {
            "x": 74.13088871912399,
            "y": 133.2477718360071
        },
        {
            "x": 109.66335625159152,
            "y": 151.3256939139292
        },
        {
            "x": 64.78023936847464,
            "y": 181.2477718360071
        },
        {
            "x": 162.02699261522793,
            "y": 247.94907053730583
        },
        {
            "x": 170.130888719124,
            "y": 211.79322638146164
        },
        {
            "x": 166.39062897886424,
            "y": 159.4295900178253
        },
        {
            "x": 172.0010185892539,
            "y": 110.80621339444863
        },
        {
            "x": 153.92309651133178,
            "y": 96.46855105678634
        },
        {
            "x": 142.7023172905526,
            "y": 73.40361599185124
        },
        {
            "x": 136.46855105678637,
            "y": 73.40361599185124
        },
        {
            "x": 153.92309651133178,
            "y": 59.06595365418887
        },
        {
            "x": 182.59842118665645,
            "y": 29.76725235548763
        },
        {
            "x": 198.80621339444866,
            "y": 27.89712248535772
        },
        {
            "x": 150.80621339444866,
            "y": 30.390628978864203
        },
        {
            "x": 184.46855105678637,
            "y": 58.44257703081231
        },
        {
            "x": 188.2088107970461,
            "y": 42.85816144639673
        },
        {
            "x": 199.4295900178253,
            "y": 51.585434173669434
        },
        {
            "x": 208.156862745098,
            "y": 27.89712248535772
        },
        {
            "x": 205.0399796282149,
            "y": 7.949070537305755
        },
        {
            "x": 188.2088107970461,
            "y": 8.572447160682392
        },
        {
            "x": 178.23478482302014,
            "y": 14.806213394448621
        },
        {
            "x": 226.85816144639676,
            "y": 6.7023172905525525
        },
        {
            "x": 239.32569391392923,
            "y": 11.06595365418887
        },
        {
            "x": 247.4295900178253,
            "y": 28.520499108734356
        },
        {
            "x": 231.22179781003308,
            "y": 30.390628978864203
        },
        {
            "x": 223.11790170613702,
            "y": 39.74127832951361
        },
        {
            "x": 245.55946014769546,
            "y": 54.70231729055256
        },
        {
            "x": 269.8711484593838,
            "y": 67.16984975808501
        },
        {
            "x": 251.16984975808504,
            "y": 98.9620575502928
        },
        {
            "x": 269.2477718360072,
            "y": 110.80621339444863
        },
        {
            "x": 299.16984975808504,
            "y": 133.2477718360071
        },
        {
            "x": 296.0529666412019,
            "y": 103.32569391392919
        },
        {
            "x": 292.9360835243188,
            "y": 69.03997962821488
        },
        {
            "x": 327.22179781003314,
            "y": 90.85816144639672
        },
        {
            "x": 337.19582378405903,
            "y": 69.03997962821488
        },
        {
            "x": 284.20881079704606,
            "y": 165.66335625159152
        },
        {
            "x": 296.0529666412019,
            "y": 29.76725235548763
        },
        {
            "x": 284.83218742042277,
            "y": 34.13088871912395
        },
        {
            "x": 285.45556404379926,
            "y": 23.533486121721403
        },
        {
            "x": 271.7412783295137,
            "y": 11.06595365418887
        },
        {
            "x": 260.52049910873444,
            "y": 12.312706900942144
        },
        {
            "x": 268.0010185892539,
            "y": 6.7023172905525525
        },
        {
            "x": 292.3127069009422,
            "y": 1.715304303539525
        },
        {
            "x": 317.2477718360072,
            "y": 4.83218742042264
        },
        {
            "x": 329.09192768016294,
            "y": 2.3386809269161626
        },
        {
            "x": 344.6763432645785,
            "y": 4.208810797046074
        },
        {
            "x": 360.8841354723708,
            "y": 38.49452508276034
        },
        {
            "x": 334.7023172905526,
            "y": 45.975044563279845
        },
        {
            "x": 327.22179781003314,
            "y": 24.156862745097968
        },
        {
            "x": 315.3776419658773,
            "y": 29.76725235548763
        },
        {
            "x": 466.8581614463967,
            "y": 50.33868092691616
        },
        {
            "x": 499.8971224853577,
            "y": 80.88413547237074
        },
        {
            "x": 485.5594601476954,
            "y": 128.88413547237073
        },
        {
            "x": 509.8711484593838,
            "y": 150.0789406671759
        },
        {
            "x": 452.52049910873444,
            "y": 170.65036923860453
        },
        {
            "x": 444.41660300483835,
            "y": 142.59842118665645
        },
        {
            "x": 410.7542653425007,
            "y": 118.28673287496812
        },
        {
            "x": 428.83218742042277,
            "y": 52.20881079704608
        },
        {
            "x": 413.8711484593838,
            "y": 58.44257703081231
        },
        {
            "x": 412.6243952126305,
            "y": 39.74127832951361
        },
        {
            "x": 436.93608352431886,
            "y": 14.806213394448621
        },
        {
            "x": 459.3776419658772,
            "y": 11.06595365418887
        },
        {
            "x": 476.83218742042277,
            "y": 31.014005602240836
        },
        {
            "x": 456.2607588489941,
            "y": 34.75426534250059
        },
        {
            "x": 426.33868092691625,
            "y": 12.312706900942144
        },
        {
            "x": 322.8581614463967,
            "y": 12.936083524318782
        },
        {
            "x": 357.143875732111,
            "y": 1.715304303539525
        },
        {
            "x": 378.33868092691625,
            "y": 3.5854341736694373
        },
        {
            "x": 390.80621339444866,
            "y": 4.208810797046074
        },
        {
            "x": 495.32569391392934,
            "y": 1.715304303539454
        },
        {
            "x": 522.7542653425008,
            "y": 19.79322638146158
        },
        {
            "x": 532.1049146931501,
            "y": 43.48153806977322
        },
        {
            "x": 540.8321874204229,
            "y": 55.94907053730568
        },
        {
            "x": 541.4555640437995,
            "y": 72.15686274509792
        },
        {
            "x": 550.1828367710723,
            "y": 25.403615991851172
        },
        {
            "x": 546.4425770308125,
            "y": 6.70231729055248
        },
        {
            "x": 550.8062133944488,
            "y": 6.70231729055248
        },
        {
            "x": 578.8581614463968,
            "y": 7.9490705373056825
        },
        {
            "x": 585.091927680163,
            "y": 38.49452508276027
        },
        {
            "x": 595.6893302775657,
            "y": 4.832187420422569
        },
        {
            "x": 617.5075120957475,
            "y": 35.37764196587715
        },
        {
            "x": 636.8321874204229,
            "y": 6.70231729055248
        },
        {
            "x": 631.84517443341,
            "y": 6.70231729055248
        },
        {
            "x": 649.9230965113319,
            "y": 23.53348612172126
        },
        {
            "x": 657.4036159918514,
            "y": 9.195823784058959
        },
        {
            "x": 674.2347848230203,
            "y": 28.520499108734285
        },
        {
            "x": 690.4425770308126,
            "y": 7.9490705373056825
        },
        {
            "x": 681.091927680163,
            "y": 1.715304303539454
        },
        {
            "x": 694.8062133944488,
            "y": 16.676343264578463
        },
        {
            "x": 704.7802393684749,
            "y": 16.676343264578463
        },
        {
            "x": 712.884135472371,
            "y": 23.53348612172126
        },
        {
            "x": 687.3256939139295,
            "y": 55.325693913929115
        },
        {
            "x": 697.2997198879553,
            "y": 47.221797810032974
        },
        {
            "x": 727.8451744334099,
            "y": 32.88413547237067
        },
        {
            "x": 741.5594601476955,
            "y": 26.650369238604373
        },
        {
            "x": 732.2088107970462,
            "y": 8.572447160682321
        },
        {
            "x": 727.8451744334099,
            "y": 3.585434173669366
        },
        {
            "x": 762.1308887191242,
            "y": 29.76725235548756
        },
        {
            "x": 778.9620575502929,
            "y": 30.390628978864125
        },
        {
            "x": 783.949070537306,
            "y": 19.16984975808494
        },
        {
            "x": 781.4555640437994,
            "y": 2.338680926916091
        },
        {
            "x": 796.4166030048385,
            "y": 50.33868092691609
        },
        {
            "x": 782.7023172905527,
            "y": 143.84517443340962
        },
        {
            "x": 747.7932263814617,
            "y": 123.89712248535768
        },
        {
            "x": 729.7153043035398,
            "y": 72.78023936847457
        },
        {
            "x": 617.5075120957475,
            "y": 95.84517443340965
        },
        {
            "x": 836.7282913165266,
            "y": 34.13088871912395
        },
        {
            "x": 825.5075120957474,
            "y": 22.286732874968127
        },
        {
            "x": 814.9101094983448,
            "y": 23.533486121721403
        },
        {
            "x": 807.4295900178253,
            "y": 11.06595365418887
        },
        {
            "x": 835.4815380697735,
            "y": 16.676343264578534
        },
        {
            "x": 850.4425770308123,
            "y": 12.312706900942144
        },
        {
            "x": 858.5464731347085,
            "y": 12.312706900942144
        },
        {
            "x": 867.2737458619812,
            "y": 21.03997962821485
        },
        {
            "x": 874.7542653425006,
            "y": 38.49452508276034
        },
        {
            "x": 890.9620575502928,
            "y": 24.156862745097968
        },
        {
            "x": 901.5594601476954,
            "y": 23.533486121721403
        },
        {
            "x": 912.156862745098,
            "y": 31.014005602240836
        },
        {
            "x": 905.2997198879552,
            "y": 16.676343264578534
        },
        {
            "x": 925.2477718360072,
            "y": 50.33868092691616
        },
        {
            "x": 942.7023172905526,
            "y": 67.16984975808501
        },
        {
            "x": 935.8451744334099,
            "y": 80.26075884899412
        },
        {
            "x": 927.7412783295136,
            "y": 96.46855105678634
        },
        {
            "x": 922.1308887191241,
            "y": 109.55946014769542
        },
        {
            "x": 912.7802393684748,
            "y": 110.80621339444863
        },
        {
            "x": 931.4815380697735,
            "y": 155.68933027756555
        },
        {
            "x": 942.0789406671761,
            "y": 160.0529666412019
        },
        {
            "x": 919.014005602241,
            "y": 207.42959001782526
        },
        {
            "x": 904.0529666412019,
            "y": 226.130888719124
        },
        {
            "x": 910.9101094983447,
            "y": 161.92309651133178
        },
        {
            "x": 890.3386809269163,
            "y": 165.66335625159152
        },
        {
            "x": 861.039979628215,
            "y": 160.0529666412019
        },
        {
            "x": 826.7542653425006,
            "y": 216.15686274509804
        },
        {
            "x": 1014.3906289788642,
            "y": 175.01400560224087
        },
        {
            "x": 1008.7802393684746,
            "y": 64.05296664120189
        },
        {
            "x": 992.5724471606825,
            "y": 2.3386809269161626
        },
        {
            "x": 986.3386809269163,
            "y": 2.3386809269161626
        },
        {
            "x": 280.26075884899416,
            "y": 278.8062133944486
        },
        {
            "x": -217.19378660555142,
            "y": 558.078940667176
        },
        {
            "x": 15.56823398255623,
            "y": 580.223752377205
        },
        {
            "x": 245.0264279624894,
            "y": 199.22040789559975
        },
        {
            "x": 104.61171224342586,
            "y": 34.511377795265275
        },
        {
            "x": 125.37425404944591,
            "y": 39.64850154108468
        },
        {
            "x": 12.785625286904054,
            "y": 60.19699652436227
        },
        {
            "x": 23.059872778542847,
            "y": 55.916060069512774
        },
        {
            "x": 133.5080333136599,
            "y": 7.327431306970968
        },
        {
            "x": 158.9796052200144,
            "y": 1.7622139156666141
        },
        {
            "x": 341.3474981966031,
            "y": 149.13345137386045
        },
        {
            "x": 365.3207423437604,
            "y": 1.976260738409074
        },
        {
            "x": 301.53478916650283,
            "y": 2.02977244409468
        },
        {
            "x": 245.0264279624894,
            "y": 86.20368548757288
        },
        {
            "x": 212.27726408289078,
            "y": 25.949504885566235
        },
        {
            "x": 795.5548560561347,
            "y": 116.38428749426181
        },
        {
            "x": 929.9762607384091,
            "y": 71.96957177519838
        },
        {
            "x": 998.6852908387435,
            "y": 79.88930421666996
        },
        {
            "x": 942.1769296347301,
            "y": 1.548167092924154
        },
        {
            "x": 753.6016787986098,
            "y": 13.96288281198769
        }
    ]
}