{
    "img_id": "660.jpg",
    "human_num": 207,
    "points": [
        {
            "x": 264.61967266245335,
            "y": 448.89735861286675
        },
        {
            "x": 277.3138875384864,
            "y": 325.7634743153461
        },
        {
            "x": 127.52215200129642,
            "y": 327.03289580294944
        },
        {
            "x": 76.74529249716423,
            "y": 202.62959001782554
        },
        {
            "x": 4.388267703775793,
            "y": 195.01306109220562
        },
        {
            "x": 152.91058175336258,
            "y": 163.27752390212297
        },
        {
            "x": 202.41801976989154,
            "y": 210.24611894344528
        },
        {
            "x": 457.5717387781559,
            "y": 337.18826770377586
        },
        {
            "x": 481.69074704261874,
            "y": 324.4940528277428
        },
        {
            "x": 597.2081024145195,
            "y": 363.8461189434453
        },
        {
            "x": 740.6527305136931,
            "y": 479.3634743153461
        },
        {
            "x": 776.1965321665855,
            "y": 443.81967266245346
        },
        {
            "x": 691.1452924971641,
            "y": 354.9601685302221
        },
        {
            "x": 656.8709123318749,
            "y": 316.8775239021229
        },
        {
            "x": 565.472565224437,
            "y": 277.5254577864205
        },
        {
            "x": 620.0576891913789,
            "y": 278.7948792740238
        },
        {
            "x": 750.8081024145196,
            "y": 285.1419867120403
        },
        {
            "x": 863.7866148112137,
            "y": 285.1419867120403
        },
        {
            "x": 863.7866148112137,
            "y": 344.80479662939564
        },
        {
            "x": 951.3766974558418,
            "y": 398.1204991087345
        },
        {
            "x": 995.8064495219572,
            "y": 295.2973586128668
        },
        {
            "x": 814.2791767946848,
            "y": 262.2923999351808
        },
        {
            "x": 800.3155404310485,
            "y": 234.36512720790807
        },
        {
            "x": 697.4923999351806,
            "y": 220.4014908442717
        },
        {
            "x": 689.8758710095609,
            "y": 201.3601685302221
        },
        {
            "x": 698.7618214227838,
            "y": 186.1271106789825
        },
        {
            "x": 743.1915734888995,
            "y": 196.2824825798089
        },
        {
            "x": 607.363474315346,
            "y": 193.7436396046023
        },
        {
            "x": 542.6229784475773,
            "y": 215.32380489385847
        },
        {
            "x": 180.83785448063531,
            "y": 134.08082968724693
        },
        {
            "x": 159.2576891913791,
            "y": 142.96678010047003
        },
        {
            "x": 14.543639604602218,
            "y": 71.879176794685
        },
        {
            "x": 31.046118943445205,
            "y": 19.832895802949412
        },
        {
            "x": 69.12876357154435,
            "y": 18.56347431534617
        },
        {
            "x": 97.05603629881708,
            "y": 22.371738778156036
        },
        {
            "x": 141.48578836493277,
            "y": 33.79653216658577
        },
        {
            "x": 166.87421811699895,
            "y": 38.87421811699902
        },
        {
            "x": 190.99322638146165,
            "y": 104.88413547237094
        },
        {
            "x": 234.15355695997414,
            "y": 115.03950737319732
        },
        {
            "x": 288.7386809269162,
            "y": 136.61967266245355
        },
        {
            "x": 333.1684329930319,
            "y": 123.92545778642058
        },
        {
            "x": 175.7601685302219,
            "y": 32.20975530708144
        },
        {
            "x": 82.45768919137895,
            "y": 9.994879274023582
        },
        {
            "x": 63.41636687732934,
            "y": 6.186614811213646
        },
        {
            "x": 74.20644952195745,
            "y": 1.74363960460209
        },
        {
            "x": 100.2295900178252,
            "y": 4.917193323610334
        },
        {
            "x": 101.49901150542853,
            "y": 12.533722249230207
        },
        {
            "x": 116.73206935666819,
            "y": 6.8213255550152665
        },
        {
            "x": 123.71388753848639,
            "y": 1.74363960460209
        },
        {
            "x": 151.64116026575914,
            "y": 13.803143736833519
        },
        {
            "x": 159.25768919137894,
            "y": 3.013061092205402
        },
        {
            "x": 173.22132555501528,
            "y": 15.07256522443676
        },
        {
            "x": 180.83785448063517,
            "y": 11.899011505428515
        },
        {
            "x": 197.34033381947816,
            "y": 15.70727596823845
        },
        {
            "x": 201.14859828228805,
            "y": 35.38330902608968
        },
        {
            "x": 199.87917679468472,
            "y": 61.40644952195747
        },
        {
            "x": 227.17173877815583,
            "y": 46.1733916707178
        },
        {
            "x": 207.4957057203046,
            "y": 8.09074704261858
        },
        {
            "x": 217.0163668773294,
            "y": 13.168432993031827
        },
        {
            "x": 225.90231729055253,
            "y": 36.652730513692994
        },
        {
            "x": 239.8659536541889,
            "y": 32.84446605088306
        },
        {
            "x": 241.7700858855939,
            "y": 9.994879274023582
        },
        {
            "x": 252.56016853022194,
            "y": 66.48413547237071
        },
        {
            "x": 274.7750445632798,
            "y": 47.44281315832111
        },
        {
            "x": 262.08082968724676,
            "y": 18.880829687246695
        },
        {
            "x": 257.6378544806352,
            "y": 32.20975530708144
        },
        {
            "x": 282.39157348889967,
            "y": 37.28744125749461
        },
        {
            "x": 272.8709123318749,
            "y": 1.74363960460209
        },
        {
            "x": 288.7386809269162,
            "y": 3.6477718360070224
        },
        {
            "x": 298.89405282774266,
            "y": 4.917193323610334
        },
        {
            "x": 309.04942472856914,
            "y": 12.533722249230207
        },
        {
            "x": 316.66595365418897,
            "y": 5.551904067412026
        },
        {
            "x": 314.1271106789824,
            "y": 48.71223464592443
        },
        {
            "x": 322.37835034840384,
            "y": 75.37008588559387
        },
        {
            "x": 350.3056230756766,
            "y": 102.66264786906493
        },
        {
            "x": 349.0362015880732,
            "y": 64.58000324096575
        },
        {
            "x": 340.7849619186517,
            "y": 53.789920596337595
        },
        {
            "x": 358.55686274509804,
            "y": 63.9452924971641
        },
        {
            "x": 371.2510776211311,
            "y": 98.21967266245333
        },
        {
            "x": 378.2328958029493,
            "y": 119.16512720790789
        },
        {
            "x": 398.54363960460216,
            "y": 128.68578836493268
        },
        {
            "x": 411.87256522443687,
            "y": 116.6262842327013
        },
        {
            "x": 439.165127207908,
            "y": 112.1833090260897
        },
        {
            "x": 425.83620158807327,
            "y": 77.90892886080049
        },
        {
            "x": 399.17835034840385,
            "y": 69.0229784475773
        },
        {
            "x": 376.963474315346,
            "y": 42.99983795170948
        },
        {
            "x": 368.0775239021229,
            "y": 38.55686274509792
        },
        {
            "x": 418.21967266245343,
            "y": 49.981656133527736
        },
        {
            "x": 343.3238048938583,
            "y": 3.013061092205402
        },
        {
            "x": 354.11388753848644,
            "y": 20.15025117485001
        },
        {
            "x": 354.11388753848644,
            "y": 11.899011505428515
        },
        {
            "x": 369.3469453897261,
            "y": 4.917193323610334
        },
        {
            "x": 377.5981850591476,
            "y": 4.282482579808714
        },
        {
            "x": 383.31058175336244,
            "y": 10.629590017825203
        },
        {
            "x": 399.81306109220543,
            "y": 12.533722249230207
        },
        {
            "x": 406.160168530222,
            "y": 23.958515637659943
        },
        {
            "x": 418.21967266245343,
            "y": 28.4014908442715
        },
        {
            "x": 426.47091233187496,
            "y": 42.99983795170948
        },
        {
            "x": 422.662647869065,
            "y": 23.958515637659943
        },
        {
            "x": 414.4114081996435,
            "y": 19.515540431048386
        },
        {
            "x": 416.3155404310484,
            "y": 8.72545778642027
        },
        {
            "x": 418.85438340625507,
            "y": 3.013061092205402
        },
        {
            "x": 442.97339167071783,
            "y": 23.323804893858252
        },
        {
            "x": 448.05107762113107,
            "y": 40.46099497650293
        },
        {
            "x": 430.2791767946848,
            "y": 58.23289580294922
        },
        {
            "x": 437.26099497650296,
            "y": 72.19653216658558
        },
        {
            "x": 448.6857883649327,
            "y": 73.4659536541889
        },
        {
            "x": 459.4758710095608,
            "y": 44.90397018311449
        },
        {
            "x": 465.8229784475773,
            "y": 85.52545778642029
        },
        {
            "x": 455.0328958029493,
            "y": 72.19653216658558
        },
        {
            "x": 498.19322638146167,
            "y": 76.63950737319719
        },
        {
            "x": 479.78661481121367,
            "y": 142.0147139847674
        },
        {
            "x": 503.2709123318749,
            "y": 133.12876357154425
        },
        {
            "x": 539.4494247285692,
            "y": 115.99157348889966
        },
        {
            "x": 524.8510776211311,
            "y": 103.93206935666825
        },
        {
            "x": 460.11058175336245,
            "y": 21.41967266245332
        },
        {
            "x": 452.49405282774273,
            "y": 11.899011505428515
        },
        {
            "x": 352.84446605088317,
            "y": 3.013061092205402
        },
        {
            "x": 470.26595365418893,
            "y": 27.132069356668186
        },
        {
            "x": 475.9783503484038,
            "y": 20.15025117485001
        },
        {
            "x": 483.5948792740237,
            "y": 13.803143736833519
        },
        {
            "x": 489.30727596823857,
            "y": 15.07256522443676
        },
        {
            "x": 503.90562307567654,
            "y": 27.76678010046988
        },
        {
            "x": 507.7138875384866,
            "y": 20.15025117485001
        },
        {
            "x": 503.90562307567654,
            "y": 16.34198671204007
        },
        {
            "x": 516.5998379517097,
            "y": 18.880829687246695
        },
        {
            "x": 515.3304164641063,
            "y": 30.940333819478123
        },
        {
            "x": 528.0246313401394,
            "y": 23.958515637659943
        },
        {
            "x": 526.1204991087344,
            "y": 39.191573488899614
        },
        {
            "x": 538.1800032409659,
            "y": 27.76678010046988
        },
        {
            "x": 547.7006643979905,
            "y": 98.53702803435432
        },
        {
            "x": 568.0114081996435,
            "y": 111.23124291038731
        },
        {
            "x": 599.7469453897261,
            "y": 118.84777183600715
        },
        {
            "x": 621.3271106789823,
            "y": 141.69735861286665
        },
        {
            "x": 639.0990115054286,
            "y": 153.12215200129646
        },
        {
            "x": 631.4824825798087,
            "y": 177.24116026575925
        },
        {
            "x": 667.0262842327014,
            "y": 168.35520985253612
        },
        {
            "x": 677.1816561335279,
            "y": 148.04446605088322
        },
        {
            "x": 691.1452924971641,
            "y": 151.85273051369316
        },
        {
            "x": 647.9849619186516,
            "y": 130.2725652244369
        },
        {
            "x": 647.9849619186516,
            "y": 97.26760654675108
        },
        {
            "x": 621.3271106789823,
            "y": 92.18992059633784
        },
        {
            "x": 613.7105817533625,
            "y": 108.69239993518083
        },
        {
            "x": 665.7568627450981,
            "y": 95.9981850591477
        },
        {
            "x": 655.6014908442717,
            "y": 116.30892886080055
        },
        {
            "x": 640.368432993032,
            "y": 121.3866148112138
        },
        {
            "x": 665.7568627450981,
            "y": 111.23124291038731
        },
        {
            "x": 749.5386809269163,
            "y": 164.5469453897262
        },
        {
            "x": 766.0411602657593,
            "y": 164.5469453897262
        },
        {
            "x": 810.4709123318747,
            "y": 174.70231729055263
        },
        {
            "x": 851.0923999351807,
            "y": 168.35520985253612
        },
        {
            "x": 903.1386809269161,
            "y": 137.88909415005676
        },
        {
            "x": 657.0824825798088,
            "y": 74.7353751417922
        },
        {
            "x": 665.3337222492303,
            "y": 72.83124291038725
        },
        {
            "x": 665.9684329930319,
            "y": 58.86760654675084
        },
        {
            "x": 673.5849619186517,
            "y": 58.23289580294922
        },
        {
            "x": 693.8957057203046,
            "y": 62.67587100956078
        },
        {
            "x": 694.5304164641062,
            "y": 56.96347431534584
        },
        {
            "x": 690.7221520012963,
            "y": 51.251077621130975
        },
        {
            "x": 705.955209852536,
            "y": 51.251077621130975
        },
        {
            "x": 714.2064495219574,
            "y": 53.789920596337595
        },
        {
            "x": 718.6494247285691,
            "y": 67.75355695997399
        },
        {
            "x": 724.3618214227839,
            "y": 74.7353751417922
        },
        {
            "x": 738.3254577864203,
            "y": 65.84942472856906
        },
        {
            "x": 749.1155404310484,
            "y": 56.32876357154422
        },
        {
            "x": 749.1155404310484,
            "y": 72.19653216658558
        },
        {
            "x": 793.5452924971642,
            "y": 81.08248257980874
        },
        {
            "x": 796.7188462161723,
            "y": 71.56182142278394
        },
        {
            "x": 804.9700858855939,
            "y": 76.00479662939549
        },
        {
            "x": 811.3171933236104,
            "y": 62.04116026575908
        },
        {
            "x": 830.9932263814616,
            "y": 89.33372224923022
        },
        {
            "x": 824.0114081996435,
            "y": 79.17835034840378
        },
        {
            "x": 833.5320693566683,
            "y": 76.63950737319719
        },
        {
            "x": 841.7833090260897,
            "y": 90.60314373683354
        },
        {
            "x": 870.9800032409659,
            "y": 83.62132555501536
        },
        {
            "x": 880.5006643979906,
            "y": 82.98661481121367
        },
        {
            "x": 890.0213255550154,
            "y": 80.44777183600708
        },
        {
            "x": 1013.155209852536,
            "y": 39.82628423270124
        },
        {
            "x": 974.4378544806352,
            "y": 79.17835034840378
        },
        {
            "x": 932.5469453897263,
            "y": 91.87256522443685
        },
        {
            "x": 912.8709123318749,
            "y": 109.00975530708146
        },
        {
            "x": 989.0362015880734,
            "y": 90.60314373683354
        },
        {
            "x": 975.0725652244369,
            "y": 91.23785448063516
        },
        {
            "x": 982.6890941500568,
            "y": 97.58496191865171
        },
        {
            "x": 1021.4064495219577,
            "y": 124.24281315832111
        },
        {
            "x": 1021.4064495219577,
            "y": 102.66264786906493
        },
        {
            "x": 953.4923999351806,
            "y": 131.85934208394096
        },
        {
            "x": 980.15025117485,
            "y": 156.61306109220544
        },
        {
            "x": 971.264300761627,
            "y": 167.40314373683353
        },
        {
            "x": 975.7072759682385,
            "y": 180.73206935666823
        },
        {
            "x": 992.844466050883,
            "y": 166.1337222492302
        },
        {
            "x": 994.1138875384866,
            "y": 184.54033381947818
        },
        {
            "x": 913.5056230756765,
            "y": 144.553556959974
        },
        {
            "x": 768.7915734888996,
            "y": 120.4345486955112
        },
        {
            "x": 788.4676065467509,
            "y": 131.85934208394096
        },
        {
            "x": 792.2758710095608,
            "y": 138.84116026575916
        },
        {
            "x": 780.2163668773294,
            "y": 122.97339167071782
        },
        {
            "x": 797.9882677037757,
            "y": 118.53041646410627
        },
        {
            "x": 810.0477718360071,
            "y": 119.16512720790789
        },
        {
            "x": 787.8328958029492,
            "y": 119.16512720790789
        },
        {
            "x": 277.8951244833598,
            "y": 60.704315292550675
        },
        {
            "x": 383.77324636148154,
            "y": 31.037981626217015
        },
        {
            "x": 255.38962997786533,
            "y": -3.039940451705108
        },
        {
            "x": 2.7143053025406783,
            "y": 5.1438757321111375
        },
        {
            "x": 16.01300660124195,
            "y": 7.189829778065163
        },
        {
            "x": 557.5347891665028,
            "y": 137.36087612302435
        },
        {
            "x": 354.6184012066367,
            "y": 44.143484818676654
        }
    ]
}