{
    "img_id": "96.jpg",
    "human_num": 18,
    "points": [
        {
            "x": 204.0,
            "y": 264.5
        },
        {
            "x": 164.0,
            "y": 298.5
        },
        {
            "x": 130.0,
            "y": 232.0
        },
        {
            "x": 168.5,
            "y": 134.5
        },
        {
            "x": 74.0,
            "y": 188.5
        },
        {
            "x": 74.5,
            "y": 169.0
        },
        {
            "x": 53.0,
            "y": 129.0
        },
        {
            "x": 43.5,
            "y": 111.5
        },
        {
            "x": 135.5,
            "y": 92.5
        },
        {
            "x": 136.0,
            "y": 52.0
        },
        {
            "x": 111.0,
            "y": 68.5
        },
        {
            "x": 103.5,
            "y": 58.5
        },
        {
            "x": 50.5,
            "y": 131.0
        },
        {
            "x": 42.5,
            "y": 113.5
        },
        {
            "x": 73.5,
            "y": 44.5
        },
        {
            "x": 78.5,
            "y": 26.5
        },
        {
            "x": 67.0,
            "y": 30.0
        },
        {
            "x": 62.5,
            "y": 59.0
        }
    ]
}